simpleduration-0.1.0.dist-info/metadata.json
simpleduration-0.1.0.dist-info/METADATA
simpleduration-0.1.0.dist-info/WHEEL
simpleduration-0.1.0.dist-info/DESCRIPTION.rst
simpleduration-0.1.0.dist-info/RECORD
simpleduration-0.1.0.dist-info/top_level.txt
simpleduration/__init__.py
simpleduration/duration.py
simpleduration/test/test_durations.py
simpleduration/test/__init__.py
