Metadata-Version: 2.0
Name: simpleduration
Version: 0.1.0
Summary: simple duration parsing library
Home-page: http://github.com/thraxil/simpleduration/
Author: Anders Pearson
Author-email: anders@columbia.edu
License: BSD
Platform: any
